ArrayPil/ArrayPil.py
ArrayPil/__init__.py
ArrayPil-1.1.dist-info/LICENSE
ArrayPil-1.1.dist-info/METADATA
ArrayPil-1.1.dist-info/WHEEL
ArrayPil-1.1.dist-info/top_level.txt
ArrayPil-1.1.dist-info/RECORD
