Metadata-Version: 2.1
Name: ArrayPil
Version: 1.1
Summary: The library that translates the Pillow expression into a Numpy array and on the contrary. It also allows you to save images from the Numpy array.
Home-page: UNKNOWN
Author: Daniil Zatsev
Author-email: yas66yelchili@gmail.com
License: UNKNOWN
Platform: UNKNOWN
License-File: LICENSE
Requires-Dist: pillow
Requires-Dist: numpy
